[{"ch":"好","startMs":315,"endMs":475},{"ch":"久","startMs":475,"endMs":625},{"ch":"不","startMs":625,"endMs":725},{"ch":"见","startMs":725,"endMs":1035},{"ch":"晏","startMs":1295,"endMs":1425},{"ch":"辞","startMs":1425,"endMs":1795},{"ch":"我","startMs":2125,"endMs":2245},{"ch":"从","startMs":2245,"endMs":2415},{"ch":"巴","startMs":2415,"endMs":2595},{"ch":"黎","startMs":2595,"endMs":2705},{"ch":"回","startMs":2705,"endMs":2865},{"ch":"来","startMs":2865,"endMs":3035},{"ch":"了","startMs":3035,"endMs":3501}]