{
  "_comment": "海报式封面 props(render-rules 10)。底图=fal 单独新出的 3:4 竖图(images/poster.png,不与视频画面重复:她仰望宣判者的暗色剪影)。",
  "image": "videos/2026/07/16/linglan-ep03-v2/images/poster.png",
  "focusY": 0.3,
  "tag": "铃兰穿越记",
  "tagVi": "Xuyên Không Thành Phu Nhân Hào Môn",
  "seal": "E03",
  "volume": { "zh": "卷一 · 惊醒", "vi": "Quyển 1 · Tỉnh Giấc" },
  "chapter": {
    "py": "yì zhēng yǎn chéng le zhōng guó xīn niáng",
    "zh": "一睁眼，成了中国新娘",
    "vi": "Mở mắt ra thành cô dâu Trung Quốc"
  },
  "episode": {
    "py": "tā zài xuān pàn wǒ de shēng sǐ",
    "zh": "他在宣判我的生死",
    "vi": "Ông ấy đang tuyên án sinh tử của tôi"
  }
}
